nexm/__init__.py
nexm/_db.py
nexm/_defaults.py
nexm/_market.py
nexm-0.0.1.dist-info/LICENSE
nexm-0.0.1.dist-info/WHEEL
nexm-0.0.1.dist-info/METADATA
nexm-0.0.1.dist-info/RECORD
