Metadata-Version: 2.1
Name: nexm
Version: 0.0.1
Summary: Nexm is key-value storage for nextcord
Author: hoopengo
Author-email: hoopengo@yandex.ru
Requires-Python: >=3.8,<4.0
Classifier: Programming Language :: Python :: 3
Classifier: Programming Language :: Python :: 3.10
Classifier: Programming Language :: Python :: 3.8
Classifier: Programming Language :: Python :: 3.9
Requires-Dist: nextcord (>=2.0.0,<3.0.0)
